LICENSE
hardwario/cloud/__init__.py
hardwario/cloud/api.py
hardwario/cloud/cli/__init__.py
hardwario/cloud/cli/codec.py
hardwario/cloud/cli/message.py
hardwario/cloud/utils.py
hardwario_cloud-1.5.0.dist-info/LICENSE
hardwario_cloud-1.5.0.dist-info/WHEEL
hardwario_cloud-1.5.0.dist-info/METADATA
hardwario_cloud-1.5.0.dist-info/entry_points.txt
hardwario_cloud-1.5.0.dist-info/RECORD
